{
  "_doc": "Synthetic-corpus labels for scripts/scorecard.sh. expect_fire/expect_absent reflect each fixture's DESIGNED INTENT (derived from tests/run.sh assert_present/assert_absent lines and tests/test-config.sh for config-app), not merely observed scanner output. See docs/scorecard.md methodology + .superpowers/sdd/task-4-report.md for the derivation reasoning.",

  "sample-app": {
    "expect_fire": ["competitor-mentions", "subscription-links-restore"],
    "expect_absent": ["private-api"]
  },
  "no-iap-app": {
    "expect_fire": [],
    "expect_absent": ["subscription-links-restore"]
  },
  "review-prompt-app": {
    "expect_fire": [],
    "expect_absent": ["subscription-links-restore"]
  },
  "root-app": {
    "expect_fire": [],
    "expect_absent": ["private-api"]
  },
  "clean-app": {
    "expect_fire": [],
    "expect_absent": [
      "siwa-parity",
      "external-purchase-link",
      "tracking-sdk-no-att",
      "export-compliance",
      "support-privacy-url",
      "analytics-privacyinfo-mismatch",
      "placeholder-metadata"
    ]
  },
  "watch-app": {
    "expect_fire": [],
    "expect_absent": ["private-api"]
  },
  "social-login-app": {
    "expect_fire": ["siwa-parity", "external-purchase-link"],
    "expect_absent": ["private-api"]
  },
  "tracking-app": {
    "expect_fire": [
      "tracking-sdk-no-att",
      "export-compliance",
      "support-privacy-url",
      "analytics-privacyinfo-mismatch",
      "placeholder-metadata"
    ],
    "expect_absent": ["private-api"]
  },
  "risky-app": {
    "expect_fire": [
      "thirdparty-payment-sdk",
      "ugc-no-moderation",
      "ats-arbitrary-loads",
      "applepay-recurring-disclosure",
      "custom-review-prompt",
      "misleading-marketing",
      "kids-wording",
      "keyboard-full-access",
      "health-icloud-sync",
      "vpn-networkextension"
    ],
    "expect_absent": ["kids-ads-analytics", "private-api"]
  },
  "risky-app-2": {
    "expect_fire": [
      "demo-account",
      "executable-code-download",
      "background-modes-unused",
      "crypto-wallet-mining",
      "remote-desktop",
      "safari-extension",
      "account-no-delete",
      "kids-ads-analytics",
      "realmoney-gambling",
      "mdm"
    ],
    "expect_absent": ["kids-wording", "ats-arbitrary-loads"]
  },
  "webview-app": {
    "expect_fire": ["webview-wrapper"],
    "expect_absent": ["private-api"]
  },
  "segmented-ui-app": {
    "expect_fire": [],
    "expect_absent": ["analytics-privacyinfo-mismatch"]
  },
  "config-app": {
    "expect_fire": [],
    "expect_absent": ["private-api"]
  },
  "audio-playback-app": {
    "expect_fire": [],
    "expect_absent": ["usage-description-crosscheck"]
  },
  "photos-picker-app": {
    "expect_fire": [],
    "expect_absent": ["usage-description-crosscheck"]
  },
  "camera-capture-app": {
    "expect_fire": ["usage-description-crosscheck"],
    "expect_absent": []
  }
}
